casho/__init__.py
casho/apps.py
casho/errors/__init__.py
casho/errors/custom_error.py
casho/errors/database_connection_error.py
casho/kafka/__init__.py
casho/kafka/Kafka_implementation/__init__.py
casho/kafka/Kafka_implementation/kafka_consumer.py
casho/kafka/Kafka_implementation/kafka_producer.py
casho/kafka/interfaces/__init__.py
casho/kafka/interfaces/iconsumer.py
casho/kafka/interfaces/iconsumer_configuration.py
casho/kafka/interfaces/ievent.py
casho/kafka/interfaces/imetadata.py
casho/kafka/interfaces/iproducer.py
casho/kafka/interfaces/iproducer_configuration.py
casho/middlewares/__init__.py
casho/middlewares/errorhandler.py
casho/middlewares/healthcheck.py
cashos-1.0.0.dist-info/METADATA
cashos-1.0.0.dist-info/WHEEL
cashos-1.0.0.dist-info/top_level.txt
cashos-1.0.0.dist-info/RECORD
